odoo/addons/base_default_lang_translate/README.rst
odoo/addons/base_default_lang_translate/__init__.py
odoo/addons/base_default_lang_translate/__manifest__.py
odoo/addons/base_default_lang_translate/i18n/base_default_lang_translate.pot
odoo/addons/base_default_lang_translate/i18n/fr.po
odoo/addons/base_default_lang_translate/models/__init__.py
odoo/addons/base_default_lang_translate/models/base.py
odoo/addons/base_default_lang_translate/models/res_lang.py
odoo/addons/base_default_lang_translate/readme/CONFIGURE.rst
odoo/addons/base_default_lang_translate/readme/CONTRIBUTORS.rst
odoo/addons/base_default_lang_translate/readme/DESCRIPTION.rst
odoo/addons/base_default_lang_translate/readme/USAGE.rst
odoo/addons/base_default_lang_translate/static/description/icon.png
odoo/addons/base_default_lang_translate/static/description/icon.svg
odoo/addons/base_default_lang_translate/static/description/index.html
odoo/addons/base_default_lang_translate/views/res_lang_views.xml
odoo12_addon_base_default_lang_translate-12.0.1.0.0.99.dev4.dist-info/METADATA
odoo12_addon_base_default_lang_translate-12.0.1.0.0.99.dev4.dist-info/WHEEL
odoo12_addon_base_default_lang_translate-12.0.1.0.0.99.dev4.dist-info/top_level.txt
odoo12_addon_base_default_lang_translate-12.0.1.0.0.99.dev4.dist-info/RECORD
